{"status": 0, "equip_list": [{"agent_user_ip": "183.141.3.182", "tr_class": "table2_tr2", "speed_aptitude": 856, "color": 0, "physical_aptitude": 3494, "attack_aptitude": 1195, "time_left": "6\u59297\u5c0f\u65f647\u5206\u949f", "skill_with_suit": "|403|411|424|428|577|578|661|", "equip_desc": "\u6ce1\u6ce1;102004;79;919;2621;464;348;97;98;101;709;104;113;114;31;671;1044;2981;10941;8;1195;864;3494;1803;856;975;1268;428|661|403|577|424|578|411;428;1;10;20;0;0;([\"summon_color\":0,\"jinjie\":([\"lx\":110,\"new_type\":0,\"core\":([\"effect\":\"#Y\u7b2c\u4e8c\u56de\u5408\u4ee5\u540e\u8fdb\u573a\u65f6\uff0c#G100%#Y\u6982\u7387\u5bf9\u8840\u91cf\u767e\u5206\u6bd4\u6700\u4f4e\u7684\u5355\u4f4d\u4f7f\u7528\u968f\u673a\u6cd5\u672f\uff1b\u6c14\u8840\u4e0a\u9650\u964d\u4f4e#R12%#Y\u3002\uff08\u6548\u679c\u4e0e\u9b54\u529b\u6709\u5173\uff09\",\"fix_st\":0,\"id\":717,\"name\":\"\u77ac\u6cd5\",]),\"cnt\":7,]),\"summon_core\":([928:({5,0,([]),}),]),])", "skill_num": 7, "equip_face_img": "102004.gif", "create_time": "2016-08-02 21:17:49", "equipid": 1606209, "rank_num": 1, "wakan": 671, "booker_num": 0, "skill": "|403|411|424|428|577|578|661|", "speed": 97, "pass_fair_show": 1, "appointed_roleid": null, "defence": 348, "final_value": 312, "fair_show_end_time": "2016-08-06 21:32:49", "visiable": 1, "attack": 464, "unit_price": 0, "min_buy_level": null, "taken_time": null, "equip_detail_url": "http://xyq.cbg.163.com/cgi-bin/equipquery.py?act=buy_show_equip_info&equip_id=1606209&server_id=378", "kindid": 70, "magic_aptitude": 1803, "equip_level": 79, "first_onsale_price": 8888800, "end_lock_time": null, "area_name": "\u6d59\u6c5f2\u533a", "defence_aptitude": 864, "status": 2, "neidan": "928", "__attached_info": {}, "is_baobao": 1, "equip_type": "102004", "price": "45000.00", "status_desc": "\u4e0a\u67b6", "equip_type_desc": "\u6ce1\u6ce1", "summon_color": 0, "equip_sn": "7mN00043AV6", "last_status_modify_time": "2016-09-26 13:12:15", "large_equip_desc": "\u6ce1\u6ce1;102004;79;919;2621;464;348;97;98;101;709;104;113;114;31;671;1044;2981;10941;8;1195;864;3494;1803;856;975;1268;428|661|403|577|424|578|411;428;1;10;20;0;0;([\"summon_color\":0,\"jinjie\":([\"lx\":110,\"new_type\":0,\"core\":([\"effect\":\"#Y\u7b2c\u4e8c\u56de\u5408\u4ee5\u540e\u8fdb\u573a\u65f6\uff0c#G100%#Y\u6982\u7387\u5bf9\u8840\u91cf\u767e\u5206\u6bd4\u6700\u4f4e\u7684\u5355\u4f4d\u4f7f\u7528\u968f\u673a\u6cd5\u672f\uff1b\u6c14\u8840\u4e0a\u9650\u964d\u4f4e#R12%#Y\u3002\uff08\u6548\u679c\u4e0e\u9b54\u529b\u6709\u5173\uff09\",\"fix_st\":0,\"id\":717,\"name\":\"\u77ac\u6cd5\",]),\"cnt\":7,]),\"summon_core\":([928:({5,0,([]),}),]),])", "used_lianshou": 0, "max_blood": 1044, "avoid_aptitude": 975, "expire_time": "2016-10-02 22:25:50", "serverid": 378, "suit_skill": 0, "reonsale_identify": "8bcf2fd148deef10e9255e0441f8cb83", "min_buyer_level": "50\u7ea7", "request_time": "2016-08-02 21:17:48", "equip_lock_time": null, "on_list_time": "2016-09-25 00:00:00", "locked": 0, "server_name": "\u7075\u9690\u5bfa", "advance_skill_num": 6, "owner_uid": 254534, "onsale_times": 6, "game_ordersn": "482_1470143868_483550868", "storage_type": 2, "value": 312, "lingxing": 110, "equip_count": 1, "growth": 1268, "equip_name": "\u6ce1\u6ce1", "skill_num_with_suit": 7, "texing": "717", "selling_time": "2016-09-18 22:25:50", "other": "(dp1\nS'is_auction_abort'\np2\nI00\nsS'seller_level'\np3\nI174\nsS'web_last_price'\np4\nI4500000\nsS'bargain'\np5\nI0\nsS'urs'\np6\nS'qlz1244544712@163.com'\np7\nsS'change_onsale_time'\np8\ncdatetime\ndatetime\np9\n(S'\\x07\\xe0\\t\\n\\x14\\x16\\x0c\\rR\\xa0'\ntRp10\nsS'vip_protection_end_time'\np11\ng9\n(S'\\x07\\xe0\\x08\\x02\\x15 1\\x00\\x00\\x00'\ntRp12\nsS'collect_num'\np13\nL424L\nsS'max_price'\np14\nI8888800\nsS'last_verified_price'\np15\nI8888800\ns."}, {"agent_user_ip": "58.221.208.154", "tr_class": "table2_tr1", "speed_aptitude": 1274, "color": 0, "physical_aptitude": 5229, "attack_aptitude": 963, "time_left": "12\u592917\u5c0f\u65f626\u5206\u949f", "skill_with_suit": "|411|424|429|573|577|578|661|", "equip_desc": "\u8774\u8776\u4ed9\u5b50;102179;69;1165;2987;322;370;151;100;79;723;79;79;79;0;708;1165;2987;10772;1;963;1235;5229;2699;1274;802;1206;661|424|577|429|578|573;429;1;10;1;4;0;([\"summon_equip2\":([\"cDesc\":\"#r\u7b49\u7ea7 65  #r\u901f\u5ea6 +21#r\u8010\u4e45\u5ea6 259#r#G#G\u7075\u529b +5#Y #G\u6cd5\u529b +9#Y#Y#r#c4DBAF4\u5957\u88c5\u6548\u679c\uff1a\u9644\u52a0\u72b6\u6001#c4DBAF4\u9ad8\u7ea7\u795e\u4f51\u590d\u751f#Y#Y#r#r\u9576\u5d4c\u6548\u679c #r+30\u901f\u5ea6 \u9576\u5d4c\u7b49\u7ea7\uff1a5\",\"iType\":9207,]),\"jinjie\":([\"new_type\":1,\"cnt\":7,\"core\":([\"fix_st\":0,\"id\":717,\"name\":\"\u77ac\u6cd5\",\"effect\":\"#Y\u7b2c\u4e8c\u56de\u5408\u4ee5\u540e\u8fdb\u573a\u65f6\uff0c#G100%#Y\u6982\u7387\u5bf9\u8840\u91cf\u767e\u5206\u6bd4\u6700\u4f4e\u7684\u5355\u4f4d\u4f7f\u7528\u968f\u673a\u6cd5\u672f\uff1b\u6c14\u8840\u4e0a\u9650\u964d\u4f4e#R12%#Y\u3002\uff08\u6548\u679c\u4e0e\u9b54\u529b\u6709\u5173\uff09\",]),\"lx\":108,]),\"summon_core\":([904:({5,0,([]),}),928:({5,0,([]),}),]),\"summon_equip1\":([\"cDesc\":\"#r\u7b49\u7ea7 65  #r\u547d\u4e2d\u7387 +7%#r\u8010\u4e45\u5ea6 275#r#G#G\u7075\u529b +5 #G\u6cd5\u529b +10#Y#Y#r#c4DBAF4\u5957\u88c5\u6548\u679c\uff1a\u9644\u52a0\u72b6\u6001#c4DBAF4\u9ad8\u7ea7\u795e\u4f51\u590d\u751f#Y#Y#r#r\u9576\u5d4c\u6548\u679c #r+24\u7075\u529b \u9576\u5d4c\u7b49\u7ea7\uff1a6\",\"iType\":9307,]),\"summon_color\":1,\"summon_equip3\":([\"cDesc\":\"#r\u7b49\u7ea7 65  #r\u9632\u5fa1 +50#r\u8010\u4e45\u5ea6 390  \u4fee\u7406\u5931\u8d25 2\u6b21#r#G#G\u6cd5\u529b +10#Y #G\u7075\u529b +5#Y#Y#r#c4DBAF4\u5957\u88c5\u6548\u679c\uff1a\u9644\u52a0\u72b6\u6001#c4DBAF4\u9ad8\u7ea7\u795e\u4f51\u590d\u751f#Y#Y#r#r\u9576\u5d4c\u6548\u679c #r+180\u6c14\u8840 \u9576\u5d4c\u7b49\u7ea7\uff1a6\",\"iType\":9107,]),])", "skill_num": 6, "equip_face_img": "102179.gif", "create_time": "2016-09-20 21:19:16", "equipid": 4799444, "rank_num": 2, "wakan": 708, "booker_num": 0, "skill": "|424|429|573|577|578|661|", "speed": 151, "pass_fair_show": 1, "appointed_roleid": null, "defence": 370, "final_value": 177, "fair_show_end_time": "2016-09-24 21:34:16", "visiable": 1, "attack": 322, "unit_price": 0, "min_buy_level": null, "taken_time": null, "equip_detail_url": "http://xyq.cbg.163.com/cgi-bin/equipquery.py?act=buy_show_equip_info&equip_id=4799444&server_id=459", "kindid": 65, "magic_aptitude": 2699, "equip_level": 69, "first_onsale_price": 80000, "end_lock_time": null, "area_name": "\u5317\u4eac1\u533a", "defence_aptitude": 1235, "status": 2, "neidan": "904,928", "__attached_info": {"summon_equip1": {"inner_id": 1, "cDesc": "#r\u7b49\u7ea7 65  #r\u547d\u4e2d\u7387 +7%#r\u8010\u4e45\u5ea6 275#r#G#G\u7075\u529b +5 #G\u6cd5\u529b +10#Y#Y#r#c4DBAF4\u5957\u88c5\u6548\u679c\uff1a\u9644\u52a0\u72b6\u6001#c4DBAF4\u9ad8\u7ea7\u795e\u4f51\u590d\u751f#Y#Y#r#r\u9576\u5d4c\u6548\u679c #r+24\u7075\u529b \u9576\u5d4c\u7b49\u7ea7\uff1a6", "iType": 9307}, "summon_equip3": {"inner_id": 3, "cDesc": "#r\u7b49\u7ea7 65  #r\u9632\u5fa1 +50#r\u8010\u4e45\u5ea6 390  \u4fee\u7406\u5931\u8d25 2\u6b21#r#G#G\u6cd5\u529b +10#Y #G\u7075\u529b +5#Y#Y#r#c4DBAF4\u5957\u88c5\u6548\u679c\uff1a\u9644\u52a0\u72b6\u6001#c4DBAF4\u9ad8\u7ea7\u795e\u4f51\u590d\u751f#Y#Y#r#r\u9576\u5d4c\u6548\u679c #r+180\u6c14\u8840 \u9576\u5d4c\u7b49\u7ea7\uff1a6", "iType": 9107}, "summon_equip2": {"inner_id": 2, "cDesc": "#r\u7b49\u7ea7 65  #r\u901f\u5ea6 +21#r\u8010\u4e45\u5ea6 259#r#G#G\u7075\u529b +5#Y #G\u6cd5\u529b +9#Y#Y#r#c4DBAF4\u5957\u88c5\u6548\u679c\uff1a\u9644\u52a0\u72b6\u6001#c4DBAF4\u9ad8\u7ea7\u795e\u4f51\u590d\u751f#Y#Y#r#r\u9576\u5d4c\u6548\u679c #r+30\u901f\u5ea6 \u9576\u5d4c\u7b49\u7ea7\uff1a5", "iType": 9207}}, "is_baobao": 1, "equip_type": "102179", "price": "4800.00", "status_desc": "\u4e0a\u67b6", "equip_type_desc": "", "summon_color": 1, "equip_sn": "5QN000DdKaJ", "last_status_modify_time": "2016-09-25 20:39:44", "large_equip_desc": "\u8774\u8776\u4ed9\u5b50;102179;69;1165;2987;322;370;151;100;79;723;79;79;79;0;708;1165;2987;10772;1;963;1235;5229;2699;1274;802;1206;661|424|577|429|578|573;429;1;10;1;4;0;([\"summon_equip2\":([\"cDesc\":\"#r\u7b49\u7ea7 65  #r\u901f\u5ea6 +21#r\u8010\u4e45\u5ea6 259#r#G#G\u7075\u529b +5#Y #G\u6cd5\u529b +9#Y#Y#r#c4DBAF4\u5957\u88c5\u6548\u679c\uff1a\u9644\u52a0\u72b6\u6001#c4DBAF4\u9ad8\u7ea7\u795e\u4f51\u590d\u751f#Y#Y#r#r\u9576\u5d4c\u6548\u679c #r+30\u901f\u5ea6 \u9576\u5d4c\u7b49\u7ea7\uff1a5\",\"iType\":9207,]),\"jinjie\":([\"new_type\":1,\"cnt\":7,\"core\":([\"fix_st\":0,\"id\":717,\"name\":\"\u77ac\u6cd5\",\"effect\":\"#Y\u7b2c\u4e8c\u56de\u5408\u4ee5\u540e\u8fdb\u573a\u65f6\uff0c#G100%#Y\u6982\u7387\u5bf9\u8840\u91cf\u767e\u5206\u6bd4\u6700\u4f4e\u7684\u5355\u4f4d\u4f7f\u7528\u968f\u673a\u6cd5\u672f\uff1b\u6c14\u8840\u4e0a\u9650\u964d\u4f4e#R12%#Y\u3002\uff08\u6548\u679c\u4e0e\u9b54\u529b\u6709\u5173\uff09\",]),\"lx\":108,]),\"summon_core\":([904:({5,0,([]),}),928:({5,0,([]),}),]),\"summon_equip1\":([\"cDesc\":\"#r\u7b49\u7ea7 65  #r\u547d\u4e2d\u7387 +7%#r\u8010\u4e45\u5ea6 275#r#G#G\u7075\u529b +5 #G\u6cd5\u529b +10#Y#Y#r#c4DBAF4\u5957\u88c5\u6548\u679c\uff1a\u9644\u52a0\u72b6\u6001#c4DBAF4\u9ad8\u7ea7\u795e\u4f51\u590d\u751f#Y#Y#r#r\u9576\u5d4c\u6548\u679c #r+24\u7075\u529b \u9576\u5d4c\u7b49\u7ea7\uff1a6\",\"iType\":9307,]),\"summon_color\":1,\"summon_equip3\":([\"cDesc\":\"#r\u7b49\u7ea7 65  #r\u9632\u5fa1 +50#r\u8010\u4e45\u5ea6 390  \u4fee\u7406\u5931\u8d25 2\u6b21#r#G#G\u6cd5\u529b +10#Y #G\u7075\u529b +5#Y#Y#r#c4DBAF4\u5957\u88c5\u6548\u679c\uff1a\u9644\u52a0\u72b6\u6001#c4DBAF4\u9ad8\u7ea7\u795e\u4f51\u590d\u751f#Y#Y#r#r\u9576\u5d4c\u6548\u679c #r+180\u6c14\u8840 \u9576\u5d4c\u7b49\u7ea7\uff1a6\",\"iType\":9107,]),])", "used_lianshou": 0, "max_blood": 1165, "avoid_aptitude": 802, "expire_time": "2016-10-09 08:05:06", "serverid": 459, "suit_skill": 411, "reonsale_identify": "8d54a8fd5fd884d833310168f5e1056f", "min_buyer_level": "50\u7ea7", "request_time": "2016-09-20 21:19:14", "equip_lock_time": null, "on_list_time": "2016-09-25 00:00:00", "locked": 0, "server_name": "2008", "advance_skill_num": 5, "owner_uid": 665541, "onsale_times": 4, "game_ordersn": "336_1474377554_340801656", "storage_type": 2, "value": 177, "lingxing": 108, "equip_count": 1, "growth": 1206, "equip_name": "\u8774\u8776\u4ed9\u5b50", "skill_num_with_suit": 7, "texing": "717", "selling_time": "2016-09-25 08:05:06", "other": "(dp1\nS'is_auction_abort'\np2\nI00\nsS'seller_level'\np3\nI59\nsS'change_onsale_time'\np4\ncdatetime\ndatetime\np5\n(S'\\x07\\xe0\\t\\x19\\x08\\x05\\x06\\x0c\\xb5*'\ntRp6\nsS'bargain'\np7\nI1\nsS'web_last_price'\np8\nL80000L\nsS'urs'\np9\nS'zhiqiang2niao@163.com'\np10\nsS'vip_protection_end_time'\np11\ng5\n(S'\\x07\\xe0\\t\\x14\\x15\"\\x10\\x00\\x00\\x00'\ntRp12\nsS'collect_num'\np13\nL166L\nsS'max_price'\np14\nI480000\nsS'last_verified_price'\np15\nI480000\ns."}, {"agent_user_ip": "113.89.130.213", "tr_class": "table2_tr2", "speed_aptitude": 945, "color": 0, "physical_aptitude": 4017, "attack_aptitude": 1344, "time_left": "7\u59297\u5c0f\u65f619\u5206\u949f", "skill_with_suit": "|332|403|408|411|413|417|424|427|577|578|661|", "equip_desc": "\u6d77\u661f;102047;61;915;590;380;249;79;100;89;84;74;74;84;501;198;915;590;10339;2;1344;892;4017;2250;945;891;1256;417|408|577|424|403|578|332|427|411|661|413;427;1;10;0;0;0;([\"jinjie\":([\"new_type\":0,\"core\":([]),\"lx\":98,\"cnt\":6,]),\"summon_core\":([928:({1,0,([]),}),]),\"summon_color\":1,])", "skill_num": 11, "equip_face_img": "102047.gif", "create_time": "2016-09-15 21:42:40", "equipid": 1223908, "rank_num": 3, "wakan": 198, "booker_num": 0, "skill": "|332|403|408|411|413|417|424|427|577|578|661|", "speed": 79, "pass_fair_show": 1, "appointed_roleid": null, "defence": 249, "final_value": 133, "fair_show_end_time": "2016-09-19 21:57:40", "visiable": 1, "attack": 380, "unit_price": 0, "min_buy_level": null, "taken_time": null, "equip_detail_url": "http://xyq.cbg.163.com/cgi-bin/equipquery.py?act=buy_show_equip_info&equip_id=1223908&server_id=79", "kindid": 70, "magic_aptitude": 2250, "equip_level": 61, "first_onsale_price": 3999900, "end_lock_time": null, "area_name": "\u5e7f\u4e1c2\u533a", "defence_aptitude": 892, "status": 2, "neidan": "928", "__attached_info": {}, "is_baobao": 1, "equip_type": "102047", "price": "39999.00", "status_desc": "\u4e0a\u67b6", "equip_type_desc": "", "summon_color": 1, "equip_sn": "18N0006QDLr", "last_status_modify_time": "2016-09-26 07:16:03", "large_equip_desc": "\u6d77\u661f;102047;61;915;590;380;249;79;100;89;84;74;74;84;501;198;915;590;10339;2;1344;892;4017;2250;945;891;1256;417|408|577|424|403|578|332|427|411|661|413;427;1;10;0;0;0;([\"jinjie\":([\"new_type\":0,\"core\":([]),\"lx\":98,\"cnt\":6,]),\"summon_core\":([928:({1,0,([]),}),]),\"summon_color\":1,])", "used_lianshou": 0, "max_blood": 915, "avoid_aptitude": 891, "expire_time": "2016-10-03 21:57:40", "serverid": 79, "suit_skill": 0, "reonsale_identify": "a424fb2ea74bef51f1db35ae70746f7d", "min_buyer_level": "50\u7ea7", "request_time": "2016-09-15 21:42:40", "equip_lock_time": null, "on_list_time": "2016-09-22 00:00:00", "locked": 0, "server_name": "\u5982\u610f\u5c9b", "advance_skill_num": 9, "owner_uid": 83060, "onsale_times": 1, "game_ordersn": "70_1473946960_71224306", "storage_type": 2, "value": 223, "lingxing": 98, "equip_count": 1, "growth": 1256, "equip_name": "\u6d77\u661f", "skill_num_with_suit": 11, "texing": "", "selling_time": "2016-09-15 21:42:40", "other": "(dp1\nS'is_auction_abort'\np2\nI00\nsS'seller_level'\np3\nI109\nsS'bargain'\np4\nI1\nsS'web_last_price'\np5\nI3999900\nsS'urs'\np6\nS'piaoke3392641@163.com'\np7\nsS'vip_protection_end_time'\np8\ncdatetime\ndatetime\np9\n(S'\\x07\\xe0\\t\\x0f\\x159(\\x00\\x00\\x00'\ntRp10\nsS'collect_num'\np11\nL280L\nsS'max_price'\np12\nI3999900\nsS'last_verified_price'\np13\nI3999900\ns."}, {"agent_user_ip": "125.115.147.166", "tr_class": "table2_tr1", "speed_aptitude": 1472, "color": 0, "physical_aptitude": 5021, "attack_aptitude": 1603, "time_left": "13\u59299\u5c0f\u65f615\u5206\u949f", "skill_with_suit": "|401|404|411|416|422|425|434|571|", "equip_desc": "\u732b\u7075;102126;180;4912;1470;2704;909;683;99;496;204;975;198;374;0;940;5182;1670;11330;1;1603;1098;5021;2436;1472;1491;1299;571|401|434|425|404|411|422;0;1;10;49;10;0;([\"summon_equip2\":([\"iType\":9212,\"cDesc\":\"#r\u7b49\u7ea7 115  #r\u901f\u5ea6 +37 \u4f24\u5bb3 +57#r\u8010\u4e45\u5ea6 319#r#G#G\u654f\u6377 +23#Y#Y#r#c4DBAF4\u5957\u88c5\u6548\u679c\uff1a\u9644\u52a0\u72b6\u6001#c4DBAF4\u9ad8\u7ea7\u5fc5\u6740#Y#Y#r#W\u5236\u9020\u8005\uff1a\u6c11\u30a8\u3079\u4f50\u03c7#Y#r#r\u9576\u5d4c\u6548\u679c #r+60\u901f\u5ea6 \u9576\u5d4c\u7b49\u7ea7\uff1a10\",]),\"summon_equip3\":([\"iType\":9112,\"cDesc\":\"#r\u7b49\u7ea7 115  #r\u9632\u5fa1 +102 \u4f24\u5bb3 +57#r\u8010\u4e45\u5ea6 309#r#G#G\u529b\u91cf +14#Y#Y#r#c4DBAF4\u5957\u88c5\u6548\u679c\uff1a\u9644\u52a0\u72b6\u6001#c4DBAF4\u9ad8\u7ea7\u5fc5\u6740#Y#Y#r#W\u5236\u9020\u8005\uff1a\u2033\u52df\u7136\u56de\u9996\uff0e#Y#r#r\u9576\u5d4c\u6548\u679c #r+270\u6c14\u8840 \u9576\u5d4c\u7b49\u7ea7\uff1a9\",]),\"summon_color\":1,\"summon_core\":([935:({5,0,([]),}),902:({5,0,([]),}),901:({5,0,([]),}),907:({5,0,([]),}),913:({5,0,([]),}),]),\"summon_equip1\":([\"iType\":9312,\"cDesc\":\"#r\u7b49\u7ea7 115  #r\u547d\u4e2d\u7387 +18% \u4f24\u5bb3 +59#r\u8010\u4e45\u5ea6 499#r#G#G\u654f\u6377 +17#Y#Y#r#c4DBAF4\u5957\u88c5\u6548\u679c\uff1a\u9644\u52a0\u72b6\u6001#c4DBAF4\u9ad8\u7ea7\u5fc5\u6740#Y#Y#r#W\u5236\u9020\u8005\uff1a\u5b9d\u5b9d\u6740\u624b\u00b0#Y#r#r\u9576\u5d4c\u6548\u679c #r+100\u4f24\u5bb3 \u9576\u5d4c\u7b49\u7ea7\uff1a10\",]),\"jinjie\":([\"new_type\":0,\"cnt\":7,\"core\":([\"name\":\"\u529b\u7834\",\"effect\":\"#Y\u5ffd\u7565\u4eba\u7269\u89d2\u8272#G240#Y\u9632\u5fa1\u529b\uff1b\u5bf9\u53ec\u5524\u517d\u7269\u7406\u4f24\u5bb3\u7ed3\u679c\u51cf\u5c11#R5%#Y\u3002\",\"fix_st\":0,\"id\":706,]),\"lx\":110,]),])", "skill_num": 7, "equip_face_img": "297_102126.gif", "create_time": "2016-06-12 11:41:47", "equipid": 1613806, "rank_num": 4, "wakan": 940, "booker_num": 0, "skill": "|401|404|411|422|425|434|571|", "speed": 683, "pass_fair_show": 1, "appointed_roleid": null, "defence": 909, "final_value": 114, "fair_show_end_time": "2016-06-16 11:56:47", "visiable": 1, "attack": 2704, "unit_price": 0, "min_buy_level": null, "taken_time": null, "equip_detail_url": "http://xyq.cbg.163.com/cgi-bin/equipquery.py?act=buy_show_equip_info&equip_id=1613806&server_id=149", "kindid": 69, "magic_aptitude": 2436, "equip_level": 180, "first_onsale_price": 2666600, "end_lock_time": null, "area_name": "\u8ffd\u5fc6", "defence_aptitude": 1098, "status": 2, "neidan": "913,907,901,902,935", "__attached_info": {"summon_equip1": {"inner_id": 1, "cDesc": "#r\u7b49\u7ea7 115  #r\u547d\u4e2d\u7387 +18% \u4f24\u5bb3 +59#r\u8010\u4e45\u5ea6 499#r#G#G\u654f\u6377 +17#Y#Y#r#c4DBAF4\u5957\u88c5\u6548\u679c\uff1a\u9644\u52a0\u72b6\u6001#c4DBAF4\u9ad8\u7ea7\u5fc5\u6740#Y#Y#r#W\u5236\u9020\u8005\uff1a\u5b9d\u5b9d\u6740\u624b\u00b0#Y#r#r\u9576\u5d4c\u6548\u679c #r+100\u4f24\u5bb3 \u9576\u5d4c\u7b49\u7ea7\uff1a10", "iType": 9312}, "summon_equip3": {"inner_id": 3, "cDesc": "#r\u7b49\u7ea7 115  #r\u9632\u5fa1 +102 \u4f24\u5bb3 +57#r\u8010\u4e45\u5ea6 309#r#G#G\u529b\u91cf +14#Y#Y#r#c4DBAF4\u5957\u88c5\u6548\u679c\uff1a\u9644\u52a0\u72b6\u6001#c4DBAF4\u9ad8\u7ea7\u5fc5\u6740#Y#Y#r#W\u5236\u9020\u8005\uff1a\u2033\u52df\u7136\u56de\u9996\uff0e#Y#r#r\u9576\u5d4c\u6548\u679c #r+270\u6c14\u8840 \u9576\u5d4c\u7b49\u7ea7\uff1a9", "iType": 9112}, "summon_equip2": {"inner_id": 2, "cDesc": "#r\u7b49\u7ea7 115  #r\u901f\u5ea6 +37 \u4f24\u5bb3 +57#r\u8010\u4e45\u5ea6 319#r#G#G\u654f\u6377 +23#Y#Y#r#c4DBAF4\u5957\u88c5\u6548\u679c\uff1a\u9644\u52a0\u72b6\u6001#c4DBAF4\u9ad8\u7ea7\u5fc5\u6740#Y#Y#r#W\u5236\u9020\u8005\uff1a\u6c11\u30a8\u3079\u4f50\u03c7#Y#r#r\u9576\u5d4c\u6548\u679c #r+60\u901f\u5ea6 \u9576\u5d4c\u7b49\u7ea7\uff1a10", "iType": 9212}}, "is_baobao": 1, "equip_type": "102126", "price": "21111.00", "status_desc": "\u4e0a\u67b6", "equip_type_desc": "", "summon_color": 1, "equip_sn": "1xN00016U55", "last_status_modify_time": "2016-09-26 12:00:39", "large_equip_desc": "\u732b\u7075;102126;180;4912;1470;2704;909;683;99;496;204;975;198;374;0;940;5182;1670;11330;1;1603;1098;5021;2436;1472;1491;1299;571|401|434|425|404|411|422;0;1;10;49;10;0;([\"summon_equip2\":([\"iType\":9212,\"cDesc\":\"#r\u7b49\u7ea7 115  #r\u901f\u5ea6 +37 \u4f24\u5bb3 +57#r\u8010\u4e45\u5ea6 319#r#G#G\u654f\u6377 +23#Y#Y#r#c4DBAF4\u5957\u88c5\u6548\u679c\uff1a\u9644\u52a0\u72b6\u6001#c4DBAF4\u9ad8\u7ea7\u5fc5\u6740#Y#Y#r#W\u5236\u9020\u8005\uff1a\u6c11\u30a8\u3079\u4f50\u03c7#Y#r#r\u9576\u5d4c\u6548\u679c #r+60\u901f\u5ea6 \u9576\u5d4c\u7b49\u7ea7\uff1a10\",]),\"summon_equip3\":([\"iType\":9112,\"cDesc\":\"#r\u7b49\u7ea7 115  #r\u9632\u5fa1 +102 \u4f24\u5bb3 +57#r\u8010\u4e45\u5ea6 309#r#G#G\u529b\u91cf +14#Y#Y#r#c4DBAF4\u5957\u88c5\u6548\u679c\uff1a\u9644\u52a0\u72b6\u6001#c4DBAF4\u9ad8\u7ea7\u5fc5\u6740#Y#Y#r#W\u5236\u9020\u8005\uff1a\u2033\u52df\u7136\u56de\u9996\uff0e#Y#r#r\u9576\u5d4c\u6548\u679c #r+270\u6c14\u8840 \u9576\u5d4c\u7b49\u7ea7\uff1a9\",]),\"summon_color\":1,\"summon_core\":([935:({5,0,([]),}),902:({5,0,([]),}),901:({5,0,([]),}),907:({5,0,([]),}),913:({5,0,([]),}),]),\"summon_equip1\":([\"iType\":9312,\"cDesc\":\"#r\u7b49\u7ea7 115  #r\u547d\u4e2d\u7387 +18% \u4f24\u5bb3 +59#r\u8010\u4e45\u5ea6 499#r#G#G\u654f\u6377 +17#Y#Y#r#c4DBAF4\u5957\u88c5\u6548\u679c\uff1a\u9644\u52a0\u72b6\u6001#c4DBAF4\u9ad8\u7ea7\u5fc5\u6740#Y#Y#r#W\u5236\u9020\u8005\uff1a\u5b9d\u5b9d\u6740\u624b\u00b0#Y#r#r\u9576\u5d4c\u6548\u679c #r+100\u4f24\u5bb3 \u9576\u5d4c\u7b49\u7ea7\uff1a10\",]),\"jinjie\":([\"new_type\":0,\"cnt\":7,\"core\":([\"name\":\"\u529b\u7834\",\"effect\":\"#Y\u5ffd\u7565\u4eba\u7269\u89d2\u8272#G240#Y\u9632\u5fa1\u529b\uff1b\u5bf9\u53ec\u5524\u517d\u7269\u7406\u4f24\u5bb3\u7ed3\u679c\u51cf\u5c11#R5%#Y\u3002\",\"fix_st\":0,\"id\":706,]),\"lx\":110,]),])", "used_lianshou": 0, "max_blood": 5182, "avoid_aptitude": 1491, "expire_time": "2016-10-09 23:54:25", "serverid": 149, "suit_skill": 416, "reonsale_identify": "e58a5d6dbee7ad5d3b227e3a977d16af", "min_buyer_level": "50\u7ea7", "request_time": "2016-06-12 11:41:47", "equip_lock_time": null, "on_list_time": "2016-09-25 00:00:00", "locked": 0, "server_name": "\u518d\u7eed\u524d\u7f18", "advance_skill_num": 7, "owner_uid": 297920, "onsale_times": 18, "game_ordersn": "10_1465702907_11614264", "storage_type": 2, "value": 114, "lingxing": 110, "equip_count": 1, "growth": 1299, "equip_name": "\u732b\u7075", "skill_num_with_suit": 8, "texing": "706", "selling_time": "2016-09-25 23:54:25", "other": "(dp1\nS'bargain'\np2\nI1\nsS'is_auction_abort'\np3\nI00\nsS'seller_level'\np4\nI175\nsS'change_onsale_time'\np5\ncdatetime\ndatetime\np6\n(S'\\x07\\xe0\\t\\x19\\x176\\x19\\x08\\x8bI'\ntRp7\nsS'web_last_price'\np8\nI2111100\nsS'urs'\np9\nS'mwhnl_1277@163.com'\np10\nsS'vip_protection_end_time'\np11\ng6\n(S'\\x07\\xe0\\x06\\x0c\\x0b8/\\x00\\x00\\x00'\ntRp12\nsS'collect_num'\np13\nL121L\nsS'max_price'\np14\nI3444400\nsS'last_verified_price'\np15\nI3444400\ns."}, {"agent_user_ip": "116.232.132.26", "tr_class": "table2_tr2", "speed_aptitude": 1123, "color": 0, "physical_aptitude": 4151, "attack_aptitude": 966, "time_left": "10\u59294\u5c0f\u65f648\u5206\u949f", "skill_with_suit": "|403|408|411|424|553|573|577|578|661|", "equip_desc": "\u96f7\u9e1f\u4eba;102023;79;2311;1932;377;757;180;100;249;471;98;296;99;0;620;2311;1932;11900;4;966;1351;4151;1613;1123;993;1188;577|424|578|408|403|573|553|661;553;1;10;105;4;0;([\"summon_core\":([931:({5,0,([]),}),928:({5,0,([]),}),]),\"jinjie\":([\"cnt\":7,\"new_type\":0,\"core\":([\"fix_st\":0,\"effect\":\"#Y\u5bf9\u6c14\u8840\u767e\u5206\u4f4e\u4e8e70%\u7684\u5355\u4f4d\u6cd5\u672f\u4f24\u5bb3\u529b\u589e\u52a0#G65#Y\uff1b\u5bf9\u5176\u4f59\u5355\u4f4d\u6cd5\u672f\u4f24\u5bb3\u529b\u964d\u4f4e#R49#Y\u3002\",\"name\":\"\u987a\u52bf\",\"id\":712,]),\"lx\":110,]),\"summon_color\":1,\"summon_equip3\":([\"iType\":9108,\"cDesc\":\"#r\u7b49\u7ea7 75  #r\u9632\u5fa1 +50#r\u8010\u4e45\u5ea6 195  \u4fee\u7406\u5931\u8d25 1\u6b21#r#G#G\u7075\u529b +7#Y #G\u6cd5\u529b +10#Y#Y#r#c4DBAF4\u5957\u88c5\u6548\u679c\uff1a\u9644\u52a0\u72b6\u6001#c4DBAF4\u9ad8\u7ea7\u795e\u4f51\u590d\u751f#Y#Y#r#W\u5236\u9020\u8005\uff1a\u6697\u8f6c\u5927\u5510#Y#r#r\u9576\u5d4c\u6548\u679c #r+210\u6c14\u8840 \u9576\u5d4c\u7b49\u7ea7\uff1a7\",]),\"summon_equip2\":([\"iType\":9208,\"cDesc\":\"#r\u7b49\u7ea7 75  #r\u901f\u5ea6 +27#r\u8010\u4e45\u5ea6 531#r#G#G\u8010\u529b +12#Y #G\u6cd5\u529b +11#Y#Y#r#c4DBAF4\u5957\u88c5\u6548\u679c\uff1a\u9644\u52a0\u72b6\u6001#c4DBAF4\u9ad8\u7ea7\u795e\u4f51\u590d\u751f#Y#Y#r#W\u5236\u9020\u8005\uff1a\u00b0\u6d45\u79cb\u5fe7\u4f24\u03be#Y#r#r\u9576\u5d4c\u6548\u679c #r+42\u901f\u5ea6 \u9576\u5d4c\u7b49\u7ea7\uff1a7\",]),\"summon_equip1\":([\"iType\":9308,\"cDesc\":\"#r\u7b49\u7ea7 75  #r\u547d\u4e2d\u7387 +10%#r\u8010\u4e45\u5ea6 496#r#G#G\u7075\u529b +7 #G\u6cd5\u529b +9#Y#Y#r#c4DBAF4\u5957\u88c5\u6548\u679c\uff1a\u9644\u52a0\u72b6\u6001#c4DBAF4\u9ad8\u7ea7\u795e\u4f51\u590d\u751f#Y#Y#r#W\u5236\u9020\u8005\uff1a\u3041\u534a\u4e16\u766b\u72c2\u3044#Y#r#r\u9576\u5d4c\u6548\u679c #r+28\u7075\u529b \u9576\u5d4c\u7b49\u7ea7\uff1a7\",]),])", "skill_num": 8, "equip_face_img": "102023.gif", "create_time": "2016-04-04 16:17:35", "equipid": 1335648, "rank_num": 5, "wakan": 620, "booker_num": 0, "skill": "|403|408|424|553|573|577|578|661|", "speed": 180, "pass_fair_show": 1, "appointed_roleid": null, "defence": 757, "final_value": 71, "fair_show_end_time": "2016-04-08 16:32:35", "visiable": 1, "attack": 377, "unit_price": 0, "min_buy_level": null, "taken_time": null, "equip_detail_url": "http://xyq.cbg.163.com/cgi-bin/equipquery.py?act=buy_show_equip_info&equip_id=1335648&server_id=173", "kindid": 65, "magic_aptitude": 1613, "equip_level": 79, "first_onsale_price": 3200000, "end_lock_time": null, "area_name": "\u534e\u5357\u533a", "defence_aptitude": 1351, "status": 2, "neidan": "928,931", "__attached_info": {"summon_equip1": {"inner_id": 1, "cDesc": "#r\u7b49\u7ea7 75  #r\u547d\u4e2d\u7387 +10%#r\u8010\u4e45\u5ea6 496#r#G#G\u7075\u529b +7 #G\u6cd5\u529b +9#Y#Y#r#c4DBAF4\u5957\u88c5\u6548\u679c\uff1a\u9644\u52a0\u72b6\u6001#c4DBAF4\u9ad8\u7ea7\u795e\u4f51\u590d\u751f#Y#Y#r#W\u5236\u9020\u8005\uff1a\u3041\u534a\u4e16\u766b\u72c2\u3044#Y#r#r\u9576\u5d4c\u6548\u679c #r+28\u7075\u529b \u9576\u5d4c\u7b49\u7ea7\uff1a7", "iType": 9308}, "summon_equip3": {"inner_id": 3, "cDesc": "#r\u7b49\u7ea7 75  #r\u9632\u5fa1 +50#r\u8010\u4e45\u5ea6 195  \u4fee\u7406\u5931\u8d25 1\u6b21#r#G#G\u7075\u529b +7#Y #G\u6cd5\u529b +10#Y#Y#r#c4DBAF4\u5957\u88c5\u6548\u679c\uff1a\u9644\u52a0\u72b6\u6001#c4DBAF4\u9ad8\u7ea7\u795e\u4f51\u590d\u751f#Y#Y#r#W\u5236\u9020\u8005\uff1a\u6697\u8f6c\u5927\u5510#Y#r#r\u9576\u5d4c\u6548\u679c #r+210\u6c14\u8840 \u9576\u5d4c\u7b49\u7ea7\uff1a7", "iType": 9108}, "summon_equip2": {"inner_id": 2, "cDesc": "#r\u7b49\u7ea7 75  #r\u901f\u5ea6 +27#r\u8010\u4e45\u5ea6 531#r#G#G\u8010\u529b +12#Y #G\u6cd5\u529b +11#Y#Y#r#c4DBAF4\u5957\u88c5\u6548\u679c\uff1a\u9644\u52a0\u72b6\u6001#c4DBAF4\u9ad8\u7ea7\u795e\u4f51\u590d\u751f#Y#Y#r#W\u5236\u9020\u8005\uff1a\u00b0\u6d45\u79cb\u5fe7\u4f24\u03be#Y#r#r\u9576\u5d4c\u6548\u679c #r+42\u901f\u5ea6 \u9576\u5d4c\u7b49\u7ea7\uff1a7", "iType": 9208}}, "is_baobao": 1, "equip_type": "102023", "price": "16000.00", "status_desc": "\u4e0a\u67b6", "equip_type_desc": "", "summon_color": 1, "equip_sn": "0oN0004ZniO", "last_status_modify_time": "2016-09-22 19:27:17", "large_equip_desc": "\u96f7\u9e1f\u4eba;102023;79;2311;1932;377;757;180;100;249;471;98;296;99;0;620;2311;1932;11900;4;966;1351;4151;1613;1123;993;1188;577|424|578|408|403|573|553|661;553;1;10;105;4;0;([\"summon_core\":([931:({5,0,([]),}),928:({5,0,([]),}),]),\"jinjie\":([\"cnt\":7,\"new_type\":0,\"core\":([\"fix_st\":0,\"effect\":\"#Y\u5bf9\u6c14\u8840\u767e\u5206\u4f4e\u4e8e70%\u7684\u5355\u4f4d\u6cd5\u672f\u4f24\u5bb3\u529b\u589e\u52a0#G65#Y\uff1b\u5bf9\u5176\u4f59\u5355\u4f4d\u6cd5\u672f\u4f24\u5bb3\u529b\u964d\u4f4e#R49#Y\u3002\",\"name\":\"\u987a\u52bf\",\"id\":712,]),\"lx\":110,]),\"summon_color\":1,\"summon_equip3\":([\"iType\":9108,\"cDesc\":\"#r\u7b49\u7ea7 75  #r\u9632\u5fa1 +50#r\u8010\u4e45\u5ea6 195  \u4fee\u7406\u5931\u8d25 1\u6b21#r#G#G\u7075\u529b +7#Y #G\u6cd5\u529b +10#Y#Y#r#c4DBAF4\u5957\u88c5\u6548\u679c\uff1a\u9644\u52a0\u72b6\u6001#c4DBAF4\u9ad8\u7ea7\u795e\u4f51\u590d\u751f#Y#Y#r#W\u5236\u9020\u8005\uff1a\u6697\u8f6c\u5927\u5510#Y#r#r\u9576\u5d4c\u6548\u679c #r+210\u6c14\u8840 \u9576\u5d4c\u7b49\u7ea7\uff1a7\",]),\"summon_equip2\":([\"iType\":9208,\"cDesc\":\"#r\u7b49\u7ea7 75  #r\u901f\u5ea6 +27#r\u8010\u4e45\u5ea6 531#r#G#G\u8010\u529b +12#Y #G\u6cd5\u529b +11#Y#Y#r#c4DBAF4\u5957\u88c5\u6548\u679c\uff1a\u9644\u52a0\u72b6\u6001#c4DBAF4\u9ad8\u7ea7\u795e\u4f51\u590d\u751f#Y#Y#r#W\u5236\u9020\u8005\uff1a\u00b0\u6d45\u79cb\u5fe7\u4f24\u03be#Y#r#r\u9576\u5d4c\u6548\u679c #r+42\u901f\u5ea6 \u9576\u5d4c\u7b49\u7ea7\uff1a7\",]),\"summon_equip1\":([\"iType\":9308,\"cDesc\":\"#r\u7b49\u7ea7 75  #r\u547d\u4e2d\u7387 +10%#r\u8010\u4e45\u5ea6 496#r#G#G\u7075\u529b +7 #G\u6cd5\u529b +9#Y#Y#r#c4DBAF4\u5957\u88c5\u6548\u679c\uff1a\u9644\u52a0\u72b6\u6001#c4DBAF4\u9ad8\u7ea7\u795e\u4f51\u590d\u751f#Y#Y#r#W\u5236\u9020\u8005\uff1a\u3041\u534a\u4e16\u766b\u72c2\u3044#Y#r#r\u9576\u5d4c\u6548\u679c #r+28\u7075\u529b \u9576\u5d4c\u7b49\u7ea7\uff1a7\",]),])", "used_lianshou": 0, "max_blood": 2311, "avoid_aptitude": 993, "expire_time": "2016-10-06 19:27:17", "serverid": 173, "suit_skill": 411, "reonsale_identify": "468f4d3d9847570d9e51af8bba7956e9", "min_buyer_level": "50\u7ea7", "request_time": "2016-04-04 16:17:35", "equip_lock_time": null, "on_list_time": "2016-09-26 00:00:00", "locked": 0, "server_name": "\u900d\u9065\u57ce", "advance_skill_num": 7, "owner_uid": 284009, "onsale_times": 21, "game_ordersn": "50_1459757855_51228531", "storage_type": 2, "value": 71, "lingxing": 110, "equip_count": 1, "growth": 1188, "equip_name": "\u96f7\u9e1f\u4eba", "skill_num_with_suit": 9, "texing": "712", "selling_time": "2016-09-22 19:27:17", "other": "(dp1\nS'is_auction_abort'\np2\nI00\nsS'seller_level'\np3\nI69\nsS'web_last_price'\np4\nI1600000\nsS'bargain'\np5\nI0\nsS'urs'\np6\nS'ruanyiyang3@163.com'\np7\nsS'change_onsale_time'\np8\ncdatetime\ndatetime\np9\n(S'\\x07\\xe0\\x06\\x02\\n\\x1f3\\x05g\\xe7'\ntRp10\nsS'vip_protection_end_time'\np11\ng9\n(S'\\x07\\xe0\\x04\\x04\\x10 #\\x00\\x00\\x00'\ntRp12\nsS'collect_num'\np13\nL75L\nsS'max_price'\np14\nI3200000\nsS'last_verified_price'\np15\nI3200000\ns."}, {"agent_user_ip": "125.120.14.182", "tr_class": "table2_tr1", "speed_aptitude": 1299, "color": 0, "physical_aptitude": 4012, "attack_aptitude": 1600, "time_left": "13\u59292\u5c0f\u65f652\u5206\u949f", "skill_with_suit": "|401|405|411|416|425|", "equip_desc": "\u9ed1\u5c71\u8001\u5996;102073;79;1059;482;1712;448;206;0;105;103;787;101;101;0;510;1256;622;7372;16;1600;1107;4012;1429;1299;1348;1286;405|411|425|401;0;1;0;0;4;0;([\"summon_core\":([919:({2,0,([]),}),901:({5,0,([]),}),]),\"summon_equip3\":([\"cDesc\":\"#r\u7b49\u7ea7 75  #r\u9632\u5fa1 +71 \u4f24\u5bb3 +40#r\u8010\u4e45\u5ea6 75  \u4fee\u7406\u5931\u8d25 2\u6b21#Y#r#c4DBAF4\u5957\u88c5\u6548\u679c\uff1a\u9644\u52a0\u72b6\u6001#c4DBAF4\u9ad8\u7ea7\u5fc5\u6740#Y#Y#r#W\u5236\u9020\u8005\uff1a\u2190\u4e0a\u5e1d\u7684\u53f3\u624b#Y#r#r\u9576\u5d4c\u6548\u679c #r+210\u6c14\u8840 \u9576\u5d4c\u7b49\u7ea7\uff1a7\",\"iType\":9108,]),\"summon_equip1\":([\"cDesc\":\"#r\u7b49\u7ea7 75  #r\u547d\u4e2d\u7387 +11% \u4f24\u5bb3 +26#r\u8010\u4e45\u5ea6 19  \u4fee\u7406\u5931\u8d25 1\u6b21#r#G#G\u529b\u91cf +15#Y#Y#r#c4DBAF4\u5957\u88c5\u6548\u679c\uff1a\u9644\u52a0\u72b6\u6001#c4DBAF4\u9ad8\u7ea7\u5fc5\u6740#Y#Y#r#r\u9576\u5d4c\u6548\u679c #r+70\u4f24\u5bb3 \u9576\u5d4c\u7b49\u7ea7\uff1a7\",\"iType\":9308,]),\"summon_color\":1,\"summon_equip2\":([\"cDesc\":\"#r\u7b49\u7ea7 75  #r\u901f\u5ea6 +27 \u4f24\u5bb3 +39#r\u8010\u4e45\u5ea6 384#r#G#G\u4f53\u8d28 +6#Y#Y#r#c4DBAF4\u5957\u88c5\u6548\u679c\uff1a\u9644\u52a0\u72b6\u6001#c4DBAF4\u9ad8\u7ea7\u5fc5\u6740#Y#Y#r#W\u5236\u9020\u8005\uff1a\uff2f\uff4f\u2032\u9893\u5e9f\u3001#Y#r#r\u9576\u5d4c\u6548\u679c #r+42\u901f\u5ea6 \u9576\u5d4c\u7b49\u7ea7\uff1a7\",\"iType\":9208,]),\"jinjie\":([\"new_type\":0,\"lx\":110,\"cnt\":7,\"core\":([\"effect\":\"#Y\u7b2c\u4e8c\u56de\u5408\u4ee5\u540e\u8fdb\u573a\u65f6\uff0c#G100%#Y\u6982\u7387\u5bf9\u6c14\u8840\u767e\u5206\u6bd4\u6700\u4f4e\u7684\u5355\u4f4d\u53d1\u52a8\u4e00\u6b21\u653b\u51fb\uff1b\u6c14\u8840\u4e0a\u9650\u964d\u4f4e#R6%#Y\u3002\",\"name\":\"\u77ac\u51fb\",\"fix_st\":0,\"id\":716,]),]),])", "skill_num": 4, "equip_face_img": "102073.gif", "create_time": "2016-04-21 23:42:22", "equipid": 1450775, "rank_num": 6, "wakan": 510, "booker_num": 0, "skill": "|401|405|411|425|", "speed": 206, "pass_fair_show": 1, "appointed_roleid": null, "defence": 448, "final_value": 69, "fair_show_end_time": "2016-04-25 23:57:22", "visiable": 1, "attack": 1712, "unit_price": 0, "min_buy_level": null, "taken_time": null, "equip_detail_url": "http://xyq.cbg.163.com/cgi-bin/equipquery.py?act=buy_show_equip_info&equip_id=1450775&server_id=378", "kindid": 65, "magic_aptitude": 1429, "equip_level": 79, "first_onsale_price": 777700, "end_lock_time": null, "area_name": "\u6d59\u6c5f2\u533a", "defence_aptitude": 1107, "status": 2, "neidan": "901,919", "__attached_info": {"summon_equip1": {"inner_id": 1, "cDesc": "#r\u7b49\u7ea7 75  #r\u547d\u4e2d\u7387 +11% \u4f24\u5bb3 +26#r\u8010\u4e45\u5ea6 19  \u4fee\u7406\u5931\u8d25 1\u6b21#r#G#G\u529b\u91cf +15#Y#Y#r#c4DBAF4\u5957\u88c5\u6548\u679c\uff1a\u9644\u52a0\u72b6\u6001#c4DBAF4\u9ad8\u7ea7\u5fc5\u6740#Y#Y#r#r\u9576\u5d4c\u6548\u679c #r+70\u4f24\u5bb3 \u9576\u5d4c\u7b49\u7ea7\uff1a7", "iType": 9308}, "summon_equip3": {"inner_id": 3, "cDesc": "#r\u7b49\u7ea7 75  #r\u9632\u5fa1 +71 \u4f24\u5bb3 +40#r\u8010\u4e45\u5ea6 75  \u4fee\u7406\u5931\u8d25 2\u6b21#Y#r#c4DBAF4\u5957\u88c5\u6548\u679c\uff1a\u9644\u52a0\u72b6\u6001#c4DBAF4\u9ad8\u7ea7\u5fc5\u6740#Y#Y#r#W\u5236\u9020\u8005\uff1a\u2190\u4e0a\u5e1d\u7684\u53f3\u624b#Y#r#r\u9576\u5d4c\u6548\u679c #r+210\u6c14\u8840 \u9576\u5d4c\u7b49\u7ea7\uff1a7", "iType": 9108}, "summon_equip2": {"inner_id": 2, "cDesc": "#r\u7b49\u7ea7 75  #r\u901f\u5ea6 +27 \u4f24\u5bb3 +39#r\u8010\u4e45\u5ea6 384#r#G#G\u4f53\u8d28 +6#Y#Y#r#c4DBAF4\u5957\u88c5\u6548\u679c\uff1a\u9644\u52a0\u72b6\u6001#c4DBAF4\u9ad8\u7ea7\u5fc5\u6740#Y#Y#r#W\u5236\u9020\u8005\uff1a\uff2f\uff4f\u2032\u9893\u5e9f\u3001#Y#r#r\u9576\u5d4c\u6548\u679c #r+42\u901f\u5ea6 \u9576\u5d4c\u7b49\u7ea7\uff1a7", "iType": 9208}}, "is_baobao": 1, "equip_type": "102073", "price": "5500.00", "status_desc": "\u4e0a\u67b6", "equip_type_desc": "", "summon_color": 1, "equip_sn": "7mN0002ymzJ", "last_status_modify_time": "2016-09-25 17:31:08", "large_equip_desc": "\u9ed1\u5c71\u8001\u5996;102073;79;1059;482;1712;448;206;0;105;103;787;101;101;0;510;1256;622;7372;16;1600;1107;4012;1429;1299;1348;1286;405|411|425|401;0;1;0;0;4;0;([\"summon_core\":([919:({2,0,([]),}),901:({5,0,([]),}),]),\"summon_equip3\":([\"cDesc\":\"#r\u7b49\u7ea7 75  #r\u9632\u5fa1 +71 \u4f24\u5bb3 +40#r\u8010\u4e45\u5ea6 75  \u4fee\u7406\u5931\u8d25 2\u6b21#Y#r#c4DBAF4\u5957\u88c5\u6548\u679c\uff1a\u9644\u52a0\u72b6\u6001#c4DBAF4\u9ad8\u7ea7\u5fc5\u6740#Y#Y#r#W\u5236\u9020\u8005\uff1a\u2190\u4e0a\u5e1d\u7684\u53f3\u624b#Y#r#r\u9576\u5d4c\u6548\u679c #r+210\u6c14\u8840 \u9576\u5d4c\u7b49\u7ea7\uff1a7\",\"iType\":9108,]),\"summon_equip1\":([\"cDesc\":\"#r\u7b49\u7ea7 75  #r\u547d\u4e2d\u7387 +11% \u4f24\u5bb3 +26#r\u8010\u4e45\u5ea6 19  \u4fee\u7406\u5931\u8d25 1\u6b21#r#G#G\u529b\u91cf +15#Y#Y#r#c4DBAF4\u5957\u88c5\u6548\u679c\uff1a\u9644\u52a0\u72b6\u6001#c4DBAF4\u9ad8\u7ea7\u5fc5\u6740#Y#Y#r#r\u9576\u5d4c\u6548\u679c #r+70\u4f24\u5bb3 \u9576\u5d4c\u7b49\u7ea7\uff1a7\",\"iType\":9308,]),\"summon_color\":1,\"summon_equip2\":([\"cDesc\":\"#r\u7b49\u7ea7 75  #r\u901f\u5ea6 +27 \u4f24\u5bb3 +39#r\u8010\u4e45\u5ea6 384#r#G#G\u4f53\u8d28 +6#Y#Y#r#c4DBAF4\u5957\u88c5\u6548\u679c\uff1a\u9644\u52a0\u72b6\u6001#c4DBAF4\u9ad8\u7ea7\u5fc5\u6740#Y#Y#r#W\u5236\u9020\u8005\uff1a\uff2f\uff4f\u2032\u9893\u5e9f\u3001#Y#r#r\u9576\u5d4c\u6548\u679c #r+42\u901f\u5ea6 \u9576\u5d4c\u7b49\u7ea7\uff1a7\",\"iType\":9208,]),\"jinjie\":([\"new_type\":0,\"lx\":110,\"cnt\":7,\"core\":([\"effect\":\"#Y\u7b2c\u4e8c\u56de\u5408\u4ee5\u540e\u8fdb\u573a\u65f6\uff0c#G100%#Y\u6982\u7387\u5bf9\u6c14\u8840\u767e\u5206\u6bd4\u6700\u4f4e\u7684\u5355\u4f4d\u53d1\u52a8\u4e00\u6b21\u653b\u51fb\uff1b\u6c14\u8840\u4e0a\u9650\u964d\u4f4e#R6%#Y\u3002\",\"name\":\"\u77ac\u51fb\",\"fix_st\":0,\"id\":716,]),]),])", "used_lianshou": 0, "max_blood": 1256, "avoid_aptitude": 1348, "expire_time": "2016-10-09 17:31:08", "serverid": 378, "suit_skill": 416, "reonsale_identify": "5135aa94b71d18cbc560fcd2dd579194", "min_buyer_level": "50\u7ea7", "request_time": "2016-04-21 23:42:20", "equip_lock_time": null, "on_list_time": "2016-09-22 00:00:00", "locked": 0, "server_name": "\u7075\u9690\u5bfa", "advance_skill_num": 4, "owner_uid": 326287, "onsale_times": 97, "game_ordersn": "482_1461253340_483395380", "storage_type": 2, "value": 116, "lingxing": 110, "equip_count": 1, "growth": 1286, "equip_name": "\u9ed1\u5c71\u8001\u5996", "skill_num_with_suit": 5, "texing": "716", "selling_time": "2016-09-25 17:31:08", "other": "(dp1\nS'is_auction_abort'\np2\nI00\nsS'seller_level'\np3\nI50\nsS'web_last_price'\np4\nI610000\nsS'bargain'\np5\nI0\nsS'urs'\np6\nS'ccccs7895@163.com'\np7\nsS'change_onsale_time'\np8\ncdatetime\ndatetime\np9\n(S'\\x07\\xe0\\t\\x14\\x12:7\\x04\\x85\\xcf'\ntRp10\nsS'vip_protection_end_time'\np11\ng9\n(S'\\x07\\xe0\\x04\\x15\\x179\\x16\\x00\\x00\\x00'\ntRp12\nsS'collect_num'\np13\nL147L\nsS'max_price'\np14\nI777700\nsS'last_verified_price'\np15\nI777700\ns."}, {"agent_user_ip": "60.181.158.238", "tr_class": "table2_tr2", "speed_aptitude": 1287, "color": 0, "physical_aptitude": 3688, "attack_aptitude": 1443, "time_left": "9\u592910\u5c0f\u65f643\u5206\u949f", "skill_with_suit": "|301|304|416|425|434|595|", "equip_desc": "\u753b\u9b42;102211;119;3773;1032;1464;454;219;80;425;129;654;129;155;0;643;3773;1032;6503;4;1443;850;3688;2276;1287;1325;1271;304|595|301|425|416|434;0;1;10;8;6;0;([\"jinjie\":([\"new_type\":1,\"cnt\":7,\"core\":([\"fix_st\":0,\"effect\":\"#Y\u5ffd\u7565\u4eba\u7269\u89d2\u8272#G158#Y\u9632\u5fa1\u529b\uff1b\u5bf9\u53ec\u5524\u517d\u7269\u7406\u4f24\u5bb3\u7ed3\u679c\u51cf\u5c11#R7%#Y\u3002\",\"name\":\"\u529b\u7834\",\"id\":706,]),\"lx\":98,]),\"summon_color\":0,\"summon_core\":([935:({1,0,([]),}),902:({5,0,([]),}),901:({5,0,([]),}),907:({5,0,([]),}),]),])", "skill_num": 6, "equip_face_img": "102211.gif", "create_time": "2016-06-26 23:45:14", "equipid": 1859963, "rank_num": 7, "wakan": 643, "booker_num": 0, "skill": "|301|304|416|425|434|595|", "speed": 219, "pass_fair_show": 1, "appointed_roleid": null, "defence": 454, "final_value": 67, "fair_show_end_time": "2016-07-01 00:00:14", "visiable": 1, "attack": 1464, "unit_price": 0, "min_buy_level": null, "taken_time": null, "equip_detail_url": "http://xyq.cbg.163.com/cgi-bin/equipquery.py?act=buy_show_equip_info&equip_id=1859963&server_id=416", "kindid": 66, "magic_aptitude": 2276, "equip_level": 119, "first_onsale_price": 145000, "end_lock_time": null, "area_name": "\u6d59\u6c5f4\u533a", "defence_aptitude": 850, "status": 2, "neidan": "907,901,902,935", "__attached_info": {}, "is_baobao": 1, "equip_type": "102211", "price": "950.00", "status_desc": "\u4e0a\u67b6", "equip_type_desc": "", "summon_color": 0, "equip_sn": "9BN0001r7qA", "last_status_modify_time": "2016-09-22 01:21:43", "large_equip_desc": "\u753b\u9b42;102211;119;3773;1032;1464;454;219;80;425;129;654;129;155;0;643;3773;1032;6503;4;1443;850;3688;2276;1287;1325;1271;304|595|301|425|416|434;0;1;10;8;6;0;([\"jinjie\":([\"new_type\":1,\"cnt\":7,\"core\":([\"fix_st\":0,\"effect\":\"#Y\u5ffd\u7565\u4eba\u7269\u89d2\u8272#G158#Y\u9632\u5fa1\u529b\uff1b\u5bf9\u53ec\u5524\u517d\u7269\u7406\u4f24\u5bb3\u7ed3\u679c\u51cf\u5c11#R7%#Y\u3002\",\"name\":\"\u529b\u7834\",\"id\":706,]),\"lx\":98,]),\"summon_color\":0,\"summon_core\":([935:({1,0,([]),}),902:({5,0,([]),}),901:({5,0,([]),}),907:({5,0,([]),}),]),])", "used_lianshou": 0, "max_blood": 3773, "avoid_aptitude": 1325, "expire_time": "2016-10-06 01:21:43", "serverid": 416, "suit_skill": 0, "reonsale_identify": "4ad3c85dc488d46f5f91fa4fabee3af3", "min_buyer_level": "50\u7ea7", "request_time": "2016-06-26 23:45:14", "equip_lock_time": null, "on_list_time": "2016-09-25 00:00:00", "locked": 0, "server_name": "\u7ecd\u5174\u9274\u6e56", "advance_skill_num": 4, "owner_uid": 7153, "onsale_times": 10, "game_ordersn": "569_1466955914_570478516", "storage_type": 2, "value": 67, "lingxing": 98, "equip_count": 1, "growth": 1271, "equip_name": "\u753b\u9b42", "skill_num_with_suit": 6, "texing": "706", "selling_time": "2016-09-22 01:21:43", "other": "(dp1\nS'is_auction_abort'\np2\nI00\nsS'seller_level'\np3\nI109\nsS'bargain'\np4\nI0\nsS'change_onsale_time'\np5\ncdatetime\ndatetime\np6\n(S'\\x07\\xe0\\x08\\x07\\x173+\\x04G\\xb0'\ntRp7\nsS'urs'\np8\nS'chenhaomintae@163.com'\np9\nsS'vip_protection_end_time'\np10\ng6\n(S'\\x07\\xe0\\x06\\x1b\\x00\\x00\\x0e\\x00\\x00\\x00'\ntRp11\nsS'collect_num'\np12\nL65L\nsS'max_price'\np13\nI145000\nsS'last_verified_price'\np14\nI145000\ns."}, {"agent_user_ip": "123.146.197.187", "tr_class": "table2_tr1", "speed_aptitude": 1494, "color": 0, "physical_aptitude": 3862, "attack_aptitude": 1554, "time_left": "7\u592920\u5c0f\u65f635\u5206\u949f", "skill_with_suit": "|401|403|404|408|411|416|417|425|571|", "equip_desc": "\u9b3c\u5c06;102076;119;4103;900;2016;713;425;100;412;144;761;138;204;0;673;4103;900;5049;16;1554;1380;3862;1467;1494;1033;1277;401|425|571|416|417|403|404|408;0;1;10;0;7;5;([\"summon_color\":1,\"summon_equip2\":([\"cDesc\":\"#r\u7b49\u7ea7 115  #r\u901f\u5ea6 +41 \u4f24\u5bb3 +60#r\u8010\u4e45\u5ea6 629#r#G#G\u529b\u91cf +25#Y#Y#r#c4DBAF4\u5957\u88c5\u6548\u679c\uff1a\u9644\u52a0\u72b6\u6001#c4DBAF4\u9ad8\u7ea7\u795e\u4f51\u590d\u751f#Y#Y#r#W\u5236\u9020\u8005\uff1a\u2032\u5fc3\u9b54\u22252or#Y#r#r\u9576\u5d4c\u6548\u679c #r+60\u901f\u5ea6 \u9576\u5d4c\u7b49\u7ea7\uff1a10\",\"iType\":9212,]),\"jinjie\":([\"core\":([\"name\":\"\u529b\u7834\",\"fix_st\":0,\"id\":706,\"effect\":\"#Y\u5ffd\u7565\u4eba\u7269\u89d2\u8272#G158#Y\u9632\u5fa1\u529b\uff1b\u5bf9\u53ec\u5524\u517d\u7269\u7406\u4f24\u5bb3\u7ed3\u679c\u51cf\u5c11#R7%#Y\u3002\",]),\"new_type\":0,\"cnt\":7,\"lx\":110,]),\"summon_core\":([935:({5,0,([]),}),901:({5,0,([]),}),907:({5,0,([]),}),904:({5,0,([]),}),]),\"summon_equip1\":([\"cDesc\":\"#r\u7b49\u7ea7 115  #r\u4f24\u5bb3 +58 \u547d\u4e2d\u7387 +18%#r\u8010\u4e45\u5ea6 500#r#G#G\u529b\u91cf +26#Y#Y#r#c4DBAF4\u5957\u88c5\u6548\u679c\uff1a\u9644\u52a0\u72b6\u6001#c4DBAF4\u9ad8\u7ea7\u795e\u4f51\u590d\u751f#Y#Y#r#W\u5236\u9020\u8005\uff1a\u4f9d\u7136\u9a84\u50b2\u516c\u4e3b#Y#r#r\u9576\u5d4c\u6548\u679c #r+100\u4f24\u5bb3 \u9576\u5d4c\u7b49\u7ea7\uff1a10\",\"iType\":9312,]),\"summon_equip3\":([\"cDesc\":\"#r\u7b49\u7ea7 115  #r\u4f24\u5bb3 +55 \u9632\u5fa1 +95#r\u8010\u4e45\u5ea6 524#r#G#G\u529b\u91cf +28#Y#Y#r#c4DBAF4\u5957\u88c5\u6548\u679c\uff1a\u9644\u52a0\u72b6\u6001#c4DBAF4\u9ad8\u7ea7\u795e\u4f51\u590d\u751f#Y#Y#r#W\u5236\u9020\u8005\uff1a\u9b54\u4e4b\u96c4\u9738\u5929\u4e0b#Y#r#r\u9576\u5d4c\u6548\u679c #r+300\u6c14\u8840 \u9576\u5d4c\u7b49\u7ea7\uff1a10\",\"iType\":9112,]),])", "skill_num": 8, "equip_face_img": "102076.gif", "create_time": "2016-08-18 11:11:20", "equipid": 1559074, "rank_num": 8, "wakan": 673, "booker_num": 0, "skill": "|401|403|404|408|416|417|425|571|", "speed": 425, "pass_fair_show": 1, "appointed_roleid": null, "defence": 713, "final_value": 65, "fair_show_end_time": "2016-08-22 11:26:20", "visiable": 1, "attack": 2016, "unit_price": 0, "min_buy_level": null, "taken_time": null, "equip_detail_url": "http://xyq.cbg.163.com/cgi-bin/equipquery.py?act=buy_show_equip_info&equip_id=1559074&server_id=377", "kindid": 66, "magic_aptitude": 1467, "equip_level": 119, "first_onsale_price": 4666600, "end_lock_time": null, "area_name": "\u6d59\u6c5f4\u533a", "defence_aptitude": 1380, "status": 2, "neidan": "904,907,901,935", "__attached_info": {"summon_equip1": {"inner_id": 1, "cDesc": "#r\u7b49\u7ea7 115  #r\u4f24\u5bb3 +58 \u547d\u4e2d\u7387 +18%#r\u8010\u4e45\u5ea6 500#r#G#G\u529b\u91cf +26#Y#Y#r#c4DBAF4\u5957\u88c5\u6548\u679c\uff1a\u9644\u52a0\u72b6\u6001#c4DBAF4\u9ad8\u7ea7\u795e\u4f51\u590d\u751f#Y#Y#r#W\u5236\u9020\u8005\uff1a\u4f9d\u7136\u9a84\u50b2\u516c\u4e3b#Y#r#r\u9576\u5d4c\u6548\u679c #r+100\u4f24\u5bb3 \u9576\u5d4c\u7b49\u7ea7\uff1a10", "iType": 9312}, "summon_equip3": {"inner_id": 3, "cDesc": "#r\u7b49\u7ea7 115  #r\u4f24\u5bb3 +55 \u9632\u5fa1 +95#r\u8010\u4e45\u5ea6 524#r#G#G\u529b\u91cf +28#Y#Y#r#c4DBAF4\u5957\u88c5\u6548\u679c\uff1a\u9644\u52a0\u72b6\u6001#c4DBAF4\u9ad8\u7ea7\u795e\u4f51\u590d\u751f#Y#Y#r#W\u5236\u9020\u8005\uff1a\u9b54\u4e4b\u96c4\u9738\u5929\u4e0b#Y#r#r\u9576\u5d4c\u6548\u679c #r+300\u6c14\u8840 \u9576\u5d4c\u7b49\u7ea7\uff1a10", "iType": 9112}, "summon_equip2": {"inner_id": 2, "cDesc": "#r\u7b49\u7ea7 115  #r\u901f\u5ea6 +41 \u4f24\u5bb3 +60#r\u8010\u4e45\u5ea6 629#r#G#G\u529b\u91cf +25#Y#Y#r#c4DBAF4\u5957\u88c5\u6548\u679c\uff1a\u9644\u52a0\u72b6\u6001#c4DBAF4\u9ad8\u7ea7\u795e\u4f51\u590d\u751f#Y#Y#r#W\u5236\u9020\u8005\uff1a\u2032\u5fc3\u9b54\u22252or#Y#r#r\u9576\u5d4c\u6548\u679c #r+60\u901f\u5ea6 \u9576\u5d4c\u7b49\u7ea7\uff1a10", "iType": 9212}}, "is_baobao": 1, "equip_type": "102076", "price": "31000.00", "status_desc": "\u4e0a\u67b6", "equip_type_desc": "", "summon_color": 1, "equip_sn": "GlN00020GUH", "last_status_modify_time": "2016-09-22 09:55:36", "large_equip_desc": "\u9b3c\u5c06;102076;119;4103;900;2016;713;425;100;412;144;761;138;204;0;673;4103;900;5049;16;1554;1380;3862;1467;1494;1033;1277;401|425|571|416|417|403|404|408;0;1;10;0;7;5;([\"summon_color\":1,\"summon_equip2\":([\"cDesc\":\"#r\u7b49\u7ea7 115  #r\u901f\u5ea6 +41 \u4f24\u5bb3 +60#r\u8010\u4e45\u5ea6 629#r#G#G\u529b\u91cf +25#Y#Y#r#c4DBAF4\u5957\u88c5\u6548\u679c\uff1a\u9644\u52a0\u72b6\u6001#c4DBAF4\u9ad8\u7ea7\u795e\u4f51\u590d\u751f#Y#Y#r#W\u5236\u9020\u8005\uff1a\u2032\u5fc3\u9b54\u22252or#Y#r#r\u9576\u5d4c\u6548\u679c #r+60\u901f\u5ea6 \u9576\u5d4c\u7b49\u7ea7\uff1a10\",\"iType\":9212,]),\"jinjie\":([\"core\":([\"name\":\"\u529b\u7834\",\"fix_st\":0,\"id\":706,\"effect\":\"#Y\u5ffd\u7565\u4eba\u7269\u89d2\u8272#G158#Y\u9632\u5fa1\u529b\uff1b\u5bf9\u53ec\u5524\u517d\u7269\u7406\u4f24\u5bb3\u7ed3\u679c\u51cf\u5c11#R7%#Y\u3002\",]),\"new_type\":0,\"cnt\":7,\"lx\":110,]),\"summon_core\":([935:({5,0,([]),}),901:({5,0,([]),}),907:({5,0,([]),}),904:({5,0,([]),}),]),\"summon_equip1\":([\"cDesc\":\"#r\u7b49\u7ea7 115  #r\u4f24\u5bb3 +58 \u547d\u4e2d\u7387 +18%#r\u8010\u4e45\u5ea6 500#r#G#G\u529b\u91cf +26#Y#Y#r#c4DBAF4\u5957\u88c5\u6548\u679c\uff1a\u9644\u52a0\u72b6\u6001#c4DBAF4\u9ad8\u7ea7\u795e\u4f51\u590d\u751f#Y#Y#r#W\u5236\u9020\u8005\uff1a\u4f9d\u7136\u9a84\u50b2\u516c\u4e3b#Y#r#r\u9576\u5d4c\u6548\u679c #r+100\u4f24\u5bb3 \u9576\u5d4c\u7b49\u7ea7\uff1a10\",\"iType\":9312,]),\"summon_equip3\":([\"cDesc\":\"#r\u7b49\u7ea7 115  #r\u4f24\u5bb3 +55 \u9632\u5fa1 +95#r\u8010\u4e45\u5ea6 524#r#G#G\u529b\u91cf +28#Y#Y#r#c4DBAF4\u5957\u88c5\u6548\u679c\uff1a\u9644\u52a0\u72b6\u6001#c4DBAF4\u9ad8\u7ea7\u795e\u4f51\u590d\u751f#Y#Y#r#W\u5236\u9020\u8005\uff1a\u9b54\u4e4b\u96c4\u9738\u5929\u4e0b#Y#r#r\u9576\u5d4c\u6548\u679c #r+300\u6c14\u8840 \u9576\u5d4c\u7b49\u7ea7\uff1a10\",\"iType\":9112,]),])", "used_lianshou": 5, "max_blood": 4103, "avoid_aptitude": 1033, "expire_time": "2016-10-04 11:14:29", "serverid": 377, "suit_skill": 411, "reonsale_identify": "8f5f39fe4feea0dba34f2911d728b74a", "min_buyer_level": "50\u7ea7", "request_time": "2016-08-18 11:11:20", "equip_lock_time": null, "on_list_time": "2016-09-24 00:00:00", "locked": 0, "server_name": "\u7ecd\u5174\u5170\u4ead", "advance_skill_num": 8, "owner_uid": 208584, "onsale_times": 7, "game_ordersn": "481_1471489880_482559295", "storage_type": 2, "value": 65, "lingxing": 110, "equip_count": 1, "growth": 1277, "equip_name": "\u9b3c\u5c06", "skill_num_with_suit": 9, "texing": "706", "selling_time": "2016-09-20 11:14:29", "other": "(dp1\nS'bargain'\np2\nI0\nsS'is_auction_abort'\np3\nI00\nsS'seller_level'\np4\nI109\nsS'web_last_price'\np5\nI3100000\nsS'change_onsale_time'\np6\ncdatetime\ndatetime\np7\n(S'\\x07\\xe0\\t\\x14\\x0b\\x0e\\x1d\\x02G\\xa5'\ntRp8\nsS'urs'\np9\nS'a616442103@163.com'\np10\nsS'vip_protection_end_time'\np11\ng7\n(S'\\x07\\xe0\\x08\\x12\\x0b\\x1a\\x14\\x00\\x00\\x00'\ntRp12\nsS'collect_num'\np13\nL69L\nsS'max_price'\np14\nI4666600\nsS'last_verified_price'\np15\nI4666600\ns."}, {"agent_user_ip": "119.131.179.165", "tr_class": "table2_tr2", "speed_aptitude": 1038, "color": 0, "physical_aptitude": 3280, "attack_aptitude": 1411, "time_left": "10\u592923\u5c0f\u65f629\u5206\u949f", "skill_with_suit": "|401|403|404|408|411|416|425|554|", "equip_desc": "\u5927\u8759\u8760;102030;79;3159;579;1238;424;151;100;359;89;482;87;89;0;454;3159;579;1252;4;1411;1140;3280;1562;1038;1313;1249;554|404|403|411|416|408|401;0;1;10;0;4;0;([\"summon_color\":1,\"summon_core\":([935:({2,0,([]),}),]),\"summon_equip2\":([\"iType\":9208,\"cDesc\":\"#r\u7b49\u7ea7 75  #r\u901f\u5ea6 +23 \u4f24\u5bb3 +35#r\u8010\u4e45\u5ea6 143#r#G#G\u4f53\u8d28 +6#Y#Y#r#c4DBAF4\u5957\u88c5\u6548\u679c\uff1a\u9644\u52a0\u72b6\u6001#c4DBAF4\u9ad8\u7ea7\u5077\u88ad#Y#Y#r#W\u5236\u9020\u8005\uff1a\u5e1d\u56fd\u00a8\u516c\u4e3b#Y#r#r\u9576\u5d4c\u6548\u679c #r+36\u901f\u5ea6 \u9576\u5d4c\u7b49\u7ea7\uff1a6\",]),\"jinjie\":([\"new_type\":0,\"lx\":104,\"core\":([\"id\":707,\"fix_st\":0,\"name\":\"\u4e89\u950b\",\"effect\":\"#Y\u5bf9\u53ec\u5524\u517d\u7269\u7406\u4f24\u5bb3\u7ed3\u679c\u589e\u52a0#G13%#Y\uff1b\u5bf9\u4eba\u7269\u89d2\u8272\u4f24\u5bb3\u7ed3\u679c\u51cf\u5c11#R39#Y\u3002\",]),\"cnt\":7,]),\"summon_equip3\":([\"iType\":9108,\"cDesc\":\"#r\u7b49\u7ea7 75  #r\u4f24\u5bb3 +40 \u9632\u5fa1 +73#r\u8010\u4e45\u5ea6 175#r#G#G\u8010\u529b -2#Y#Y#r#c4DBAF4\u5957\u88c5\u6548\u679c\uff1a\u9644\u52a0\u72b6\u6001#c4DBAF4\u9ad8\u7ea7\u5077\u88ad#Y#Y#r#W\u5236\u9020\u8005\uff1a\u5c0f\u5c0f\u3064\u7cca#Y#r#r\u9576\u5d4c\u6548\u679c #r+210\u6c14\u8840 \u9576\u5d4c\u7b49\u7ea7\uff1a7\",]),\"summon_equip1\":([\"iType\":9308,\"cDesc\":\"#r\u7b49\u7ea7 75  #r\u547d\u4e2d\u7387 +13% \u4f24\u5bb3 +40#r\u8010\u4e45\u5ea6 146#Y#r#c4DBAF4\u5957\u88c5\u6548\u679c\uff1a\u9644\u52a0\u72b6\u6001#c4DBAF4\u9ad8\u7ea7\u5077\u88ad#Y#Y#r#W\u5236\u9020\u8005\uff1a\u665a\u98ce\u543b\u5c3d\u8377\u53f6#Y#r#r\u9576\u5d4c\u6548\u679c #r+70\u4f24\u5bb3 \u9576\u5d4c\u7b49\u7ea7\uff1a7\",]),])", "skill_num": 7, "equip_face_img": "102030.gif", "create_time": "2016-05-12 00:50:57", "equipid": 1795517, "rank_num": 9, "wakan": 454, "booker_num": 0, "skill": "|401|403|404|408|411|416|554|", "speed": 151, "pass_fair_show": 1, "appointed_roleid": null, "defence": 424, "final_value": 59, "fair_show_end_time": "2016-05-16 01:05:57", "visiable": 1, "attack": 1238, "unit_price": 0, "min_buy_level": null, "taken_time": null, "equip_detail_url": "http://xyq.cbg.163.com/cgi-bin/equipquery.py?act=buy_show_equip_info&equip_id=1795517&server_id=416", "kindid": 70, "magic_aptitude": 1562, "equip_level": 79, "first_onsale_price": 450000, "end_lock_time": null, "area_name": "\u6d59\u6c5f4\u533a", "defence_aptitude": 1140, "status": 2, "neidan": "935", "__attached_info": {"summon_equip1": {"inner_id": 1, "cDesc": "#r\u7b49\u7ea7 75  #r\u547d\u4e2d\u7387 +13% \u4f24\u5bb3 +40#r\u8010\u4e45\u5ea6 146#Y#r#c4DBAF4\u5957\u88c5\u6548\u679c\uff1a\u9644\u52a0\u72b6\u6001#c4DBAF4\u9ad8\u7ea7\u5077\u88ad#Y#Y#r#W\u5236\u9020\u8005\uff1a\u665a\u98ce\u543b\u5c3d\u8377\u53f6#Y#r#r\u9576\u5d4c\u6548\u679c #r+70\u4f24\u5bb3 \u9576\u5d4c\u7b49\u7ea7\uff1a7", "iType": 9308}, "summon_equip3": {"inner_id": 3, "cDesc": "#r\u7b49\u7ea7 75  #r\u4f24\u5bb3 +40 \u9632\u5fa1 +73#r\u8010\u4e45\u5ea6 175#r#G#G\u8010\u529b -2#Y#Y#r#c4DBAF4\u5957\u88c5\u6548\u679c\uff1a\u9644\u52a0\u72b6\u6001#c4DBAF4\u9ad8\u7ea7\u5077\u88ad#Y#Y#r#W\u5236\u9020\u8005\uff1a\u5c0f\u5c0f\u3064\u7cca#Y#r#r\u9576\u5d4c\u6548\u679c #r+210\u6c14\u8840 \u9576\u5d4c\u7b49\u7ea7\uff1a7", "iType": 9108}, "summon_equip2": {"inner_id": 2, "cDesc": "#r\u7b49\u7ea7 75  #r\u901f\u5ea6 +23 \u4f24\u5bb3 +35#r\u8010\u4e45\u5ea6 143#r#G#G\u4f53\u8d28 +6#Y#Y#r#c4DBAF4\u5957\u88c5\u6548\u679c\uff1a\u9644\u52a0\u72b6\u6001#c4DBAF4\u9ad8\u7ea7\u5077\u88ad#Y#Y#r#W\u5236\u9020\u8005\uff1a\u5e1d\u56fd\u00a8\u516c\u4e3b#Y#r#r\u9576\u5d4c\u6548\u679c #r+36\u901f\u5ea6 \u9576\u5d4c\u7b49\u7ea7\uff1a6", "iType": 9208}}, "is_baobao": 1, "equip_type": "102030", "price": "3157.99", "status_desc": "\u4e0a\u67b6", "equip_type_desc": "", "summon_color": 1, "equip_sn": "74N00024IcV", "last_status_modify_time": "2016-09-23 14:07:49", "large_equip_desc": "\u5927\u8759\u8760;102030;79;3159;579;1238;424;151;100;359;89;482;87;89;0;454;3159;579;1252;4;1411;1140;3280;1562;1038;1313;1249;554|404|403|411|416|408|401;0;1;10;0;4;0;([\"summon_color\":1,\"summon_core\":([935:({2,0,([]),}),]),\"summon_equip2\":([\"iType\":9208,\"cDesc\":\"#r\u7b49\u7ea7 75  #r\u901f\u5ea6 +23 \u4f24\u5bb3 +35#r\u8010\u4e45\u5ea6 143#r#G#G\u4f53\u8d28 +6#Y#Y#r#c4DBAF4\u5957\u88c5\u6548\u679c\uff1a\u9644\u52a0\u72b6\u6001#c4DBAF4\u9ad8\u7ea7\u5077\u88ad#Y#Y#r#W\u5236\u9020\u8005\uff1a\u5e1d\u56fd\u00a8\u516c\u4e3b#Y#r#r\u9576\u5d4c\u6548\u679c #r+36\u901f\u5ea6 \u9576\u5d4c\u7b49\u7ea7\uff1a6\",]),\"jinjie\":([\"new_type\":0,\"lx\":104,\"core\":([\"id\":707,\"fix_st\":0,\"name\":\"\u4e89\u950b\",\"effect\":\"#Y\u5bf9\u53ec\u5524\u517d\u7269\u7406\u4f24\u5bb3\u7ed3\u679c\u589e\u52a0#G13%#Y\uff1b\u5bf9\u4eba\u7269\u89d2\u8272\u4f24\u5bb3\u7ed3\u679c\u51cf\u5c11#R39#Y\u3002\",]),\"cnt\":7,]),\"summon_equip3\":([\"iType\":9108,\"cDesc\":\"#r\u7b49\u7ea7 75  #r\u4f24\u5bb3 +40 \u9632\u5fa1 +73#r\u8010\u4e45\u5ea6 175#r#G#G\u8010\u529b -2#Y#Y#r#c4DBAF4\u5957\u88c5\u6548\u679c\uff1a\u9644\u52a0\u72b6\u6001#c4DBAF4\u9ad8\u7ea7\u5077\u88ad#Y#Y#r#W\u5236\u9020\u8005\uff1a\u5c0f\u5c0f\u3064\u7cca#Y#r#r\u9576\u5d4c\u6548\u679c #r+210\u6c14\u8840 \u9576\u5d4c\u7b49\u7ea7\uff1a7\",]),\"summon_equip1\":([\"iType\":9308,\"cDesc\":\"#r\u7b49\u7ea7 75  #r\u547d\u4e2d\u7387 +13% \u4f24\u5bb3 +40#r\u8010\u4e45\u5ea6 146#Y#r#c4DBAF4\u5957\u88c5\u6548\u679c\uff1a\u9644\u52a0\u72b6\u6001#c4DBAF4\u9ad8\u7ea7\u5077\u88ad#Y#Y#r#W\u5236\u9020\u8005\uff1a\u665a\u98ce\u543b\u5c3d\u8377\u53f6#Y#r#r\u9576\u5d4c\u6548\u679c #r+70\u4f24\u5bb3 \u9576\u5d4c\u7b49\u7ea7\uff1a7\",]),])", "used_lianshou": 0, "max_blood": 3159, "avoid_aptitude": 1313, "expire_time": "2016-10-07 14:07:49", "serverid": 416, "suit_skill": 425, "reonsale_identify": "3e7c4e58a6cabef45e26e5b6e1102683", "min_buyer_level": "50\u7ea7", "request_time": "2016-05-12 00:50:57", "equip_lock_time": null, "on_list_time": "2016-09-24 00:00:00", "locked": 0, "server_name": "\u7ecd\u5174\u9274\u6e56", "advance_skill_num": 7, "owner_uid": 413867, "onsale_times": 26, "game_ordersn": "569_1462985457_570414025", "storage_type": 2, "value": 59, "lingxing": 104, "equip_count": 1, "growth": 1249, "equip_name": "\u5927\u8759\u8760", "skill_num_with_suit": 8, "texing": "707", "selling_time": "2016-09-23 14:07:49", "other": "(dp1\nS'is_auction_abort'\np2\nI00\nsS'seller_level'\np3\nI69\nsS'web_last_price'\np4\nI315800\nsS'bargain'\np5\nI0\nsS'urs'\np6\nS'aaqqww02@163.com'\np7\nsS'change_onsale_time'\np8\ncdatetime\ndatetime\np9\n(S'\\x07\\xe0\\t\\x17\\x0e\\x071\\x07\\xd8\\xc0'\ntRp10\nsS'vip_protection_end_time'\np11\ng9\n(S'\\x07\\xe0\\x05\\x0c\\x01\\x059\\x00\\x00\\x00'\ntRp12\nsS'collect_num'\np13\nL67L\nsS'max_price'\np14\nI450000\nsS'last_verified_price'\np15\nI450000\ns."}, {"agent_user_ip": "115.201.207.140", "tr_class": "table2_tr1", "speed_aptitude": 1347, "color": 0, "physical_aptitude": 4485, "attack_aptitude": 1600, "time_left": "13\u59297\u5c0f\u65f651\u5206\u949f", "skill_with_suit": "|401|404|416|425|434|", "equip_desc": "\u8299\u84c9\u4ed9\u5b50;102009;99;1341;618;2162;598;260;75;115;117;964;115;121;0;623;1611;797;59999;2;1600;1319;4485;1724;1347;1637;1300;416|401|425|434;0;1;10;0;5;0;([\"summon_equip2\":([\"cDesc\":\"#r\u7b49\u7ea7 95  #r\u4f24\u5bb3 +51 \u901f\u5ea6 +36#r\u8010\u4e45\u5ea6 426#r#G#G\u529b\u91cf +23#Y#Y#r#c4DBAF4\u5957\u88c5\u6548\u679c\uff1a\u9644\u52a0\u72b6\u6001#c4DBAF4\u9ad8\u7ea7\u5438\u8840#Y#Y#r#W\u5236\u9020\u8005\uff1a\u3058\u9b54\u874e\u3074\u4ed4#Y#r#r\u9576\u5d4c\u6548\u679c #r+54\u901f\u5ea6 \u9576\u5d4c\u7b49\u7ea7\uff1a9\",\"iType\":9210,]),\"summon_equip1\":([\"cDesc\":\"#r\u7b49\u7ea7 95  #r\u4f24\u5bb3 +51 \u547d\u4e2d\u7387 +16%#r\u8010\u4e45\u5ea6 402#r#G#G\u529b\u91cf +23#Y#Y#r#c4DBAF4\u5957\u88c5\u6548\u679c\uff1a\u9644\u52a0\u72b6\u6001#c4DBAF4\u9ad8\u7ea7\u5438\u8840#Y#Y#r#W\u5236\u9020\u8005\uff1a\u5fc3\u788e\u3003\u5c0f\u8776\u300f#Y#r#r\u9576\u5d4c\u6548\u679c #r+90\u4f24\u5bb3 \u9576\u5d4c\u7b49\u7ea7\uff1a9\",\"iType\":9310,]),\"jinjie\":([\"core\":([\"name\":\"\u7075\u5203\",\"effect\":\"#Y\u7b2c\u4e8c\u56de\u5408\u4ee5\u540e\u8fdb\u573a\u65f6\uff0c#G100%#Y\u6982\u7387\u5bf9\u81ea\u8eab\u9020\u621030%\u6c14\u8840\u4e0a\u9650\u7684\u4f24\u5bb3\u5e76\u4e14\u7269\u7406\u4f24\u5bb3\u7ed3\u679c\u63d0\u9ad850%\uff0c\u6301\u7eed4\u56de\u5408\u3002\u9632\u5fa1\u529b\u3001\u6cd5\u672f\u9632\u5fa1\u529b\u964d\u4f4e#R6%#Y\u3002\uff08\u5e26\u6709\u9b3c\u9b42\u6216\u795e\u4f51\u7c7b\u6280\u80fd\u65f6\uff0c\u4f24\u5bb3\u7ed3\u679c\u53ea\u63d0\u9ad810%\uff09\",\"fix_st\":0,\"id\":718,]),\"cnt\":7,\"lx\":110,\"new_type\":0,]),\"summon_color\":1,\"summon_equip3\":([\"cDesc\":\"#r\u7b49\u7ea7 95  #r\u4f24\u5bb3 +51 \u9632\u5fa1 +93#r\u8010\u4e45\u5ea6 57#r#G#G\u529b\u91cf +23#Y#Y#r#c4DBAF4\u5957\u88c5\u6548\u679c\uff1a\u9644\u52a0\u72b6\u6001#c4DBAF4\u9ad8\u7ea7\u5438\u8840#Y#Y#r#W\u5236\u9020\u8005\uff1a\u2500\u2500\u5251\u6731\u4ed9#Y#r#r\u9576\u5d4c\u6548\u679c #r+270\u6c14\u8840 \u9576\u5d4c\u7b49\u7ea7\uff1a9\",\"iType\":9110,]),\"summon_core\":([935:({5,0,([]),}),902:({5,0,([]),}),901:({5,0,([]),}),]),])", "skill_num": 4, "equip_face_img": "102009.gif", "create_time": "2016-07-29 13:52:54", "equipid": 1767579, "rank_num": 10, "wakan": 623, "booker_num": 0, "skill": "|401|416|425|434|", "speed": 260, "pass_fair_show": 1, "appointed_roleid": null, "defence": 598, "final_value": 58, "fair_show_end_time": "2016-08-02 14:07:54", "visiable": 1, "attack": 2162, "unit_price": 0, "min_buy_level": null, "taken_time": null, "equip_detail_url": "http://xyq.cbg.163.com/cgi-bin/equipquery.py?act=buy_show_equip_info&equip_id=1767579&server_id=33", "kindid": 66, "magic_aptitude": 1724, "equip_level": 99, "first_onsale_price": 1200000, "end_lock_time": null, "area_name": "\u5c71\u4e1c3\u533a", "defence_aptitude": 1319, "status": 2, "neidan": "901,902,935", "__attached_info": {"summon_equip1": {"inner_id": 1, "cDesc": "#r\u7b49\u7ea7 95  #r\u4f24\u5bb3 +51 \u547d\u4e2d\u7387 +16%#r\u8010\u4e45\u5ea6 402#r#G#G\u529b\u91cf +23#Y#Y#r#c4DBAF4\u5957\u88c5\u6548\u679c\uff1a\u9644\u52a0\u72b6\u6001#c4DBAF4\u9ad8\u7ea7\u5438\u8840#Y#Y#r#W\u5236\u9020\u8005\uff1a\u5fc3\u788e\u3003\u5c0f\u8776\u300f#Y#r#r\u9576\u5d4c\u6548\u679c #r+90\u4f24\u5bb3 \u9576\u5d4c\u7b49\u7ea7\uff1a9", "iType": 9310}, "summon_equip3": {"inner_id": 3, "cDesc": "#r\u7b49\u7ea7 95  #r\u4f24\u5bb3 +51 \u9632\u5fa1 +93#r\u8010\u4e45\u5ea6 57#r#G#G\u529b\u91cf +23#Y#Y#r#c4DBAF4\u5957\u88c5\u6548\u679c\uff1a\u9644\u52a0\u72b6\u6001#c4DBAF4\u9ad8\u7ea7\u5438\u8840#Y#Y#r#W\u5236\u9020\u8005\uff1a\u2500\u2500\u5251\u6731\u4ed9#Y#r#r\u9576\u5d4c\u6548\u679c #r+270\u6c14\u8840 \u9576\u5d4c\u7b49\u7ea7\uff1a9", "iType": 9110}, "summon_equip2": {"inner_id": 2, "cDesc": "#r\u7b49\u7ea7 95  #r\u4f24\u5bb3 +51 \u901f\u5ea6 +36#r\u8010\u4e45\u5ea6 426#r#G#G\u529b\u91cf +23#Y#Y#r#c4DBAF4\u5957\u88c5\u6548\u679c\uff1a\u9644\u52a0\u72b6\u6001#c4DBAF4\u9ad8\u7ea7\u5438\u8840#Y#Y#r#W\u5236\u9020\u8005\uff1a\u3058\u9b54\u874e\u3074\u4ed4#Y#r#r\u9576\u5d4c\u6548\u679c #r+54\u901f\u5ea6 \u9576\u5d4c\u7b49\u7ea7\uff1a9", "iType": 9210}}, "is_baobao": 1, "equip_type": "102009", "price": "9999.00", "status_desc": "\u4e0a\u67b6", "equip_type_desc": "", "summon_color": 1, "equip_sn": "1CN0006CG4G", "last_status_modify_time": "2016-09-26 07:17:16", "large_equip_desc": "\u8299\u84c9\u4ed9\u5b50;102009;99;1341;618;2162;598;260;75;115;117;964;115;121;0;623;1611;797;59999;2;1600;1319;4485;1724;1347;1637;1300;416|401|425|434;0;1;10;0;5;0;([\"summon_equip2\":([\"cDesc\":\"#r\u7b49\u7ea7 95  #r\u4f24\u5bb3 +51 \u901f\u5ea6 +36#r\u8010\u4e45\u5ea6 426#r#G#G\u529b\u91cf +23#Y#Y#r#c4DBAF4\u5957\u88c5\u6548\u679c\uff1a\u9644\u52a0\u72b6\u6001#c4DBAF4\u9ad8\u7ea7\u5438\u8840#Y#Y#r#W\u5236\u9020\u8005\uff1a\u3058\u9b54\u874e\u3074\u4ed4#Y#r#r\u9576\u5d4c\u6548\u679c #r+54\u901f\u5ea6 \u9576\u5d4c\u7b49\u7ea7\uff1a9\",\"iType\":9210,]),\"summon_equip1\":([\"cDesc\":\"#r\u7b49\u7ea7 95  #r\u4f24\u5bb3 +51 \u547d\u4e2d\u7387 +16%#r\u8010\u4e45\u5ea6 402#r#G#G\u529b\u91cf +23#Y#Y#r#c4DBAF4\u5957\u88c5\u6548\u679c\uff1a\u9644\u52a0\u72b6\u6001#c4DBAF4\u9ad8\u7ea7\u5438\u8840#Y#Y#r#W\u5236\u9020\u8005\uff1a\u5fc3\u788e\u3003\u5c0f\u8776\u300f#Y#r#r\u9576\u5d4c\u6548\u679c #r+90\u4f24\u5bb3 \u9576\u5d4c\u7b49\u7ea7\uff1a9\",\"iType\":9310,]),\"jinjie\":([\"core\":([\"name\":\"\u7075\u5203\",\"effect\":\"#Y\u7b2c\u4e8c\u56de\u5408\u4ee5\u540e\u8fdb\u573a\u65f6\uff0c#G100%#Y\u6982\u7387\u5bf9\u81ea\u8eab\u9020\u621030%\u6c14\u8840\u4e0a\u9650\u7684\u4f24\u5bb3\u5e76\u4e14\u7269\u7406\u4f24\u5bb3\u7ed3\u679c\u63d0\u9ad850%\uff0c\u6301\u7eed4\u56de\u5408\u3002\u9632\u5fa1\u529b\u3001\u6cd5\u672f\u9632\u5fa1\u529b\u964d\u4f4e#R6%#Y\u3002\uff08\u5e26\u6709\u9b3c\u9b42\u6216\u795e\u4f51\u7c7b\u6280\u80fd\u65f6\uff0c\u4f24\u5bb3\u7ed3\u679c\u53ea\u63d0\u9ad810%\uff09\",\"fix_st\":0,\"id\":718,]),\"cnt\":7,\"lx\":110,\"new_type\":0,]),\"summon_color\":1,\"summon_equip3\":([\"cDesc\":\"#r\u7b49\u7ea7 95  #r\u4f24\u5bb3 +51 \u9632\u5fa1 +93#r\u8010\u4e45\u5ea6 57#r#G#G\u529b\u91cf +23#Y#Y#r#c4DBAF4\u5957\u88c5\u6548\u679c\uff1a\u9644\u52a0\u72b6\u6001#c4DBAF4\u9ad8\u7ea7\u5438\u8840#Y#Y#r#W\u5236\u9020\u8005\uff1a\u2500\u2500\u5251\u6731\u4ed9#Y#r#r\u9576\u5d4c\u6548\u679c #r+270\u6c14\u8840 \u9576\u5d4c\u7b49\u7ea7\uff1a9\",\"iType\":9110,]),\"summon_core\":([935:({5,0,([]),}),902:({5,0,([]),}),901:({5,0,([]),}),]),])", "used_lianshou": 0, "max_blood": 1611, "avoid_aptitude": 1637, "expire_time": "2016-10-09 22:30:02", "serverid": 33, "suit_skill": 404, "reonsale_identify": "5833aa8a9a66dd0f760cc60c6b9c306b", "min_buyer_level": "50\u7ea7", "request_time": "2016-07-29 13:52:54", "equip_lock_time": null, "on_list_time": "2016-09-23 00:00:00", "locked": 0, "server_name": "\u84ec\u83b1\u5c9b", "advance_skill_num": 4, "owner_uid": 468628, "onsale_times": 33, "game_ordersn": "120_1469771574_121053038", "storage_type": 2, "value": 85, "lingxing": 110, "equip_count": 1, "growth": 1300, "equip_name": "\u8299\u84c9\u4ed9\u5b50", "skill_num_with_suit": 5, "texing": "718", "selling_time": "2016-09-25 22:30:02", "other": "(dp1\nS'bargain'\np2\nI0\nsS'is_auction_abort'\np3\nI00\nsS'seller_level'\np4\nI92\nsS'change_onsale_time'\np5\ncdatetime\ndatetime\np6\n(S'\\x07\\xe0\\t\\x12\\r\\x032\\n\\x98\\xf0'\ntRp7\nsS'web_last_price'\np8\nI1111100\nsS'urs'\np9\nS'de3120@163.com'\np10\nsS'vip_protection_end_time'\np11\ng6\n(S'\\x07\\xe0\\x07\\x1d\\x0e\\x076\\x00\\x00\\x00'\ntRp12\nsS'collect_num'\np13\nL92L\nsS'max_price'\np14\nI1200000\nsS'last_verified_price'\np15\nI1200000\ns."}]}